Workbook

Sheet C&P
L3: Fecha: | P3: 46255.618
E4: REPORTE COLUMNARIO
E6: SOLUTIONS & PAYROLL S.A.S.
L8: Usuario: | P8: NOVACLOUD\sol-lmadrid
E10: 900.508.955-5
L12: Reporte: | P12: NOMPLCOL
E15: GTN COLUMNARIO CONSOLIDADO
L17: Página: | P17: 1
B22: Codigo Empl | C22: Nombre | F22: Apellido 1 | G22: Apellido 2 | H22: DEVENGO | V22: DEDUCCION | Z22: NO OPERA
H23: 001050 Salario | M23: 001067 Hora Dom o Fest Ordinar | Q23: 001751-Bonificacion Salarial | V23: 002205 Salud Empleado | W23: 002210 Pensión Empleado | X23: 200051 Des Anticipo de Nomina | Z23: 002221 Pensión Patrono | AA23: 002222 Riesgo Profesional | AB23: 002910 Aporte Caja Compensació | AC23: 008407 Provision Prima | AD23: 008412 Provision Cesantias | AE23: 008415 Provision Int Ces | AF23: 008402 Provision Vacaciones
H24: Valor | M24: Valor | Q24: Valor | S24: Valor | V24: Valor | W24: Valor | X24: Valor | Y24: Valor | Z24: Valor | AA24: Valor | AB24: Valor | AC24: Valor | AD24: Valor | AE24: Valor | AF24: Valor | AG24: Valor
B25: 1020781908 | C25: FRANCY MILENA | F25: ROZO | G25: GUZMAN | H25: 3500810 | M25: 300069 | Q25: 559121 | S25: 4360000 | V25: 174400 | W25: 174400 | X25: 2180000 | Y25: 2528800 | Z25: 523200 | AA25: 22800 | AB25: 174400 | AC25: 363188 | AD25: 363188 | AE25: 43600 | AF25: 181812 | AG25: 1672188
B26: 1125229719 | C26: YOSSYE HERNEY | F26: SUAREZ | G26: PEREZ | H26: 3500810 | M26: 300069 | Q26: 559121 | S26: 4360000 | V26: 174400 | W26: 174400 | X26: 2180000 | Y26: 2528800 | Z26: 523200 | AA26: 22800 | AB26: 174400 | AC26: 363188 | AD26: 363188 | AE26: 43600 | AF26: 181812 | AG26: 1672188

Sheet Invoicing
B1: COST REPORT
E2: EXCHANGE RATE | F2: CANTIDAD DIAS LABORALES | G2: 20 | Y2: SOCIAL SECURITY EMPLOYER COSTS COP | AG2: SOCIAL BENEFITS COST PROVISION | AL2: OTHER EMPLOYER COST | AO2: TOTALS
A3: EMPLOYEE CODE | B3: NAME | C3: MINIMUN GROSS SALARY | D3: USD HOURLY RATE | E3: EXCHANGE RATE | F3: HORAS A TRABAJAR EN EL MES | G3: USD AMOUNT ORDINARY SALARRY | H3: ORDINARY SALARY | J3: USD AMOUNT HOLIDAY | K3: HOLIDAY | M3: USD AMOUNT SICK LEAVE | N3: PAID LEAVE | P3: USD AMOUNT BONUS | Q3: BONUS | S3: USD AMOUNT PTO | T3: PTO | V3: USD AMOUNT PAYMENTS | W3: PAYMENTS | Y3: PENSION COST | Z3: HEALTH COST | AA3: LABOR RISK COST | AB3: FAMILY FUND COST | AC3: SENA COST | AD3: ICBF COST | AE3: TOTAL | AG3: 13TH MONTH | AH3: 14TH MONTH | AI3: INTEREST ON 14TH MONTH | AJ3: TOTAL | AL3: PERIODIC MEDICAL TEST | AM3: TOTAL | AO3: TOTAL EMPLOYEE COST | AP3: FEE | AQ3: TOTAL COP | AR3: EXCHANGE RATE | AS3: TOTAL EMPLOYEE COST USD | AT3: FEE USD | AU3: TOTAL USD
A4: =CONCATENATE('C&P'!B25) -> 1020781908 | B4: =CONCATENATE('C&P'!C25," ",'C&P'!D25," ",'C&P'!E25) -> FRANCY MILENA | C4: 3688.46 | D4: 6.5 | E4: 3205.87 | F4: 176 | G4: =H4/E4 -> 1092 | H4: ='C&P'!H25 -> 3500810 | I4: 168 | J4: =K4/E4 -> 93.599865 | K4: ='C&P'!M25 -> 300069 | L4: 8 | M4: =N4/E4 -> 0 | N4: 0 | O4: 48 | P4: =Q4/E4 -> 174.40539 | Q4: ='C&P'!Q25 -> 559121 | R4: 0 | S4: =T4/E4 -> 0 | T4: 0 | U4: 0 | V4: =W4/$E4 -> 1360.0052 | W4: =SUM($H4,$K4,$N4,$Q4,$T4) -> 4360000 | Y4: ='C&P'!Z25 -> 523200 | Z4: 0 | AA4: ='C&P'!AA25 -> 22800 | AB4: ='C&P'!AB25 -> 174400 | AC4: 0 | AD4: 0 | AE4: =SUM(Y4:AD4) -> 720400 | AG4: ='C&P'!AC25 -> 363188 | AH4: ='C&P'!AD25 -> 363188 | AI4: ='C&P'!AE25 -> 43600 | AJ4: =SUM(AG4:AI4) -> 769976 | AL4: 0 | AM4: =SUM(AL4) -> 0 | AO4: =W4+AE4+AJ4+AM4 -> 5850376 | AP4: =AO4*11% -> 643541.36 | AQ4: =AO4+AP4 -> 6493917.4 | AR4: 2995.38 | AS4: =ROUND(AO4/AR4,2) -> 1953.13 | AT4: =ROUND(AP4/AR4,2) -> 214.84 | AU4: =SUM(AS4:AT4) -> 2167.97
A5: =CONCATENATE('C&P'!B26) -> 1125229719 | B5: =CONCATENATE('C&P'!C26," ",'C&P'!D26," ",'C&P'!E26) -> YOSSYE HERNEY | C5: 3688.46 | D5: 6.5 | E5: 3205.87 | F5: 176 | G5: =H5/E5 -> 1092 | H5: ='C&P'!H26 -> 3500810 | I5: 168 | J5: =K5/E5 -> 93.599865 | K5: ='C&P'!M26 -> 300069 | L5: 8 | M5: =N5/E5 -> 0 | N5: 0 | O5: 0 | P5: =Q5/E5 -> 174.40539 | Q5: ='C&P'!Q26 -> 559121 | R5: 0 | S5: =T5/E5 -> 0 | T5: 0 | U5: 0 | V5: =W5/$E5 -> 1360.0052 | W5: =SUM($H5,$K5,$N5,$Q5,$T5) -> 4360000 | Y5: ='C&P'!Z26 -> 523200 | Z5: 0 | AA5: ='C&P'!AA26 -> 22800 | AB5: ='C&P'!AB26 -> 174400 | AC5: 0 | AD5: 0 | AE5: =SUM(Y5:AD5) -> 720400 | AG5: ='C&P'!AC26 -> 363188 | AH5: ='C&P'!AD26 -> 363188 | AI5: ='C&P'!AE26 -> 43600 | AJ5: =SUM(AG5:AI5) -> 769976 | AL5: 0 | AM5: =SUM(AL5) -> 0 | AO5: =W5+AE5+AJ5+AM5 -> 5850376 | AP5: =AO5*11% -> 643541.36 | AQ5: =AO5+AP5 -> 6493917.4 | AR5: 2995.38 | AS5: =ROUND(AO5/AR5,2) -> 1953.13 | AT5: =ROUND(AP5/AR5,2) -> 214.84 | AU5: =SUM(AS5:AT5) -> 2167.97
C6: TOTAL | G6: =SUM(G4:G5) -> 2184 | H6: =SUM(H4:H5) -> 7001620 | I6: =SUM(I4:I5) -> 336 | J6: =SUM(J4:J5) -> 187.19973 | K6: =SUM(K4:K5) -> 600138 | L6: =SUM(L4:L5) -> 16 | M6: =SUM(M4:M5) -> 0 | N6: =SUM(N4:N5) -> 0 | ... W6: =SUM(W4:W5) -> 8720000 | Y6: =SUM(Y4:Y5) -> 1046400 | Z6: =SUM(Z4:Z5) -> 0 | AA6: =SUM(AA4:AA5) -> 45600 | AB6: =SUM(AB4:AB5) -> 348800 | AC6: =SUM(AC4:AC5) -> 0 | AD6: =SUM(AD4:AD5) -> 0 | AE6: =SUM(AE4:AE5) -> 1440800 | AG6: =SUM(AG4:AG5) -> 726376 | AH6: =SUM(AH4:AH5) -> 726376 | AI6: =SUM(AI4:AI5) -> 87200 | AJ6: =SUM(AJ4:AJ5) -> 1539952 | AL6: =SUM(AL4:AL5) -> 0 | AM6: =SUM(AM4:AM5) -> 0 | AO6: =SUM(AO4:AO5) -> 11700752 | AP6: =SUM(AP4:AP5) -> 1287082.7 | AQ6: =SUM(AQ4:AQ5) -> 12987835 | AS6: =SUM(AS4:AS5) -> 3906.26 | AT6: =SUM(AT4:AT5) -> 429.68 | AU6: =SUM(AU4:AU5) -> 4335.94
A7: ______________________________ ______________________________ ______________________________ ELABORÓ REVISÓ APROBÓ
