Workbook

Sheet InvoiceDetails
B1: COST REPORT
AG2: EMPLOYER COST | AM2: OTHER EMPLOYER COST | AU2: TOTALS
A3: EMPLOYEE CODE | B3: NAME | C3: Onboarding Date | D3: Offboarding Date | E3: EE Status (onboarding/active/offboarding) | F3: Country | G3: Customer Name | H3: Payroll Month | I3: Service Type / Invoice Type | J3: ER SS rate % | K3: SALARY | L3: Rectroactive payment/Plus Compensation | M3: "Sick" Leave | N3: Alloawance 1 (Car Allowance) | O3: Unused Holidays | P3: Overtime | Q3: Bonus/Commission | R3: Deduction or Gross Amount adjustments prevous month | S3: Alloawance 2 (Mobile & Internet Allowance) | T3: Food allowance | U3: Alloawance 3 (Home/Remote work allowance) | V3: Alloawance 4 (Other allowances) | W3: Holidays | X3: Sign-on Bonus | Y3: Transport allowance | Z3: Wellness Allowance | AA3: On Call/ Plus Disponibilidad | AB3: Severance Pay (Taxable) | AC3: Lieu of Notice | AD3: Paternity/ Maternity leave | AE3: PAYMENTS | AG3: BASIC | AH3: X100 - APORTE SEG SOCIAL EMPLEADOR | AI3: X200 - APORTE INS EMPLEADOR | AJ3: 13TH MONTH (AGUINALDO) | AK3: TOTAL | AM3: OTHER | AN3: OTHER | AO3: OTHER | AP3: OTHER | AQ3: HEALT INSURANCE | AR3: EXPENSES REIMBURSEMENT | AS3: TOTAL | AU3: TOTAL EMPLOYEE COST | AV3: FEE | AW3: BANKING TAX | AX3: TOTAL | AY3: EXCHANGE RATE | AZ3: TOTAL EMPLOYEE COST USD | BA3: FEE USD | BB3: TOTAL USD
A4: =rpt_InformeNominaMes!A4 -> 701910926 | B4: =rpt_InformeNominaMes!B4 -> OSCAR JOSUE PEREZ CASCANTE | C4: =+rpt_InformeNominaMes!R4 -> 25/08/2025 | E4: Onboarding | F4: Costa Rica | G4: BIPO SANY | H4: 46266 | I4: Monthly Payroll | J4: 0.2783 | K4: =rpt_InformeNominaMes!T4 -> 1750 | L4: 0 | M4: 0 | N4: 0 | O4: 0 | P4: 0 | Q4: =+rpt_InformeNominaMes!U4+rpt_InformeNominaMes!X4 -> 171.11 | R4: 0 | S4: =+rpt_InformeNominaMes!W4 -> 30 | T4: =+rpt_InformeNominaMes!Z4 -> 0 | U4: 0 | V4: =+rpt_InformeNominaMes!Y4 -> 0 | W4: =+rpt_InformeNominaMes!AB4 -> 0 | X4: 0 | Y4: =+rpt_InformeNominaMes!V4+rpt_InformeNominaMes!AA4 -> 300 | Z4: 0 | AA4: 0 | AB4: 0 | AC4: 0 | AD4: 0 | AE4: =+SUM($K4:$AD4) -> 2251.11 | AG4: =rpt_InformeNominaMes!S4 -> 1750 | AH4: =+rpt_InformeNominaMes!AG4 -> 603.97 | AI4: =+rpt_InformeNominaMes!AH4 -> 22.51 | AJ4: =+rpt_InformeNominaMes!AQ4 -> 187.5925 | AK4: =SUM($AH4:$AJ4) -> 814.0725 | AM4: 0 | AN4: 0 | AO4: 0 | AP4: 0 | AQ4: 0 | AR4: =+rpt_InformeNominaMes!AI4 -> 0 | AS4: =SUM($AM4:$AR4) -> 0 | AU4: =SUM(AE4,AK4,AS4,AW4) -> 3090.1825 | AV4: =135*AY4 -> 135 | AW4: =25*AY4 -> 25 | AX4: =AU4+AV4 -> 3225.1825 | AY4: 1 | AZ4: =ROUND($AU4/$AY4,2) -> 3090.18 | BA4: =+AV4/AY4 -> 135 | BB4: =SUM($AZ4:$BA4) -> 3225.18 | BD4: 135
G5: TOTALES | K5: =+SUM(K4:K4) -> 1750 | L5: =+SUM(L4:L4) -> 0 | M5: =+SUM(M4:M4) -> 0 | N5: =+SUM(N4:N4) -> 0 | O5: =+SUM(O4:O4) -> 0 | P5: =+SUM(P4:P4) -> 0 | Q5: =+SUM(Q4:Q4) -> 171.11 | R5: =+SUM(R4:R4) -> 0 | ... AE5: =+SUM(AE4:AE4) -> 2251.11 | AG5: TOTAL | AH5: =+SUM(AH4:AH4) -> 603.97 | AI5: =+SUM(AI4:AI4) -> 22.51 | AJ5: =+SUM(AJ4:AJ4) -> 187.5925 | AK5: =+SUM(AK4:AK4) -> 814.0725 | AM5: =+SUM(AM4:AM4) -> 0 | AN5: =+SUM(AN4:AN4) -> 0 | AO5: =+SUM(AO4:AO4) -> 0 | AP5: =+SUM(AP4:AP4) -> 0 | AQ5: =+SUM(AQ4:AQ4) -> 0 | AR5: =+SUM(AR4:AR4) -> 0 | AS5: =+SUM(AS4:AS4) -> 0 | AU5: =+SUM(AU4:AU4) -> 3090.1825 | AV5: =+SUM(AV4:AV4) -> 135 | AW5: =+SUM(AW4:AW4) -> 25 | AX5: =+SUM(AX4:AX4) -> 3225.1825 | AZ5: =+SUM(AZ4:AZ4) -> 3090.18 | BA5: =+SUM(BA4:BA4) -> 135 | BB5: =+SUM(BB4:BB4) -> 3225.18

Sheet rpt_InformeNominaMes
B1: Informe de Nómina Movimiento Liquidado MLQ , Nómina: ('ME01') Periodo: ('20260909') -
A3: EMPLEADO | B3: NOMBRE COMPLETO | C3: DOCUMENTO IDENTIDAD | D3: CCOSTO | E3: DESC.CCOSTO | F3: OFICIO | G3: DESC. OFICIO | H3: AREA | I3: DESC.AREA | J3: PROYECTO | K3: DESC.PROYECTO | L3: GRUPO | M3: DESC.GRUPO | N3: DPTO | O3: DESC.DEPTO | P3: NIVEL | Q3: DESC.NIVEL | R3: FECHA ANTIGUEDAD | S3: SALARIO | T3: A000 - SALARIO ORDINARIO | U3: A019 - COMISIONES | V3: A023 - AUXILIO DE TRANSPORTE | W3: A024 - AUXILIO DE TELECOMUNICACIONES | X3: A025 - BONO SALARIAL | Y3: A028 - AUXILIO DE SALUD | Z3: A029 - AUXILIO ALIMENTACION | AA3: A102 - AUXILIO TRANSPORTE | AB3: G006 - VACACIONES DISFRUTADAS HABILES | AC3: H100 - APORTE SEG SOCIAL | AD3: I100 - APORTE BANCO POPULAR | AE3: R003 - RETENCION EN LA FUENTE | AF3: R004 - RETENCION EN LA FUENTE USD | AG3: X100 - APORTE SEG SOCIAL EMPLEADOR | AH3: X200 - APORTE INS EMPLEADOR | AI3: X300 - EXPENSES | AJ3: DEVENGADOS | AK3: DEDUCCIONES | AL3: APORTES DEL EMPLEADOR | AM3: NETO A PAGAR | AN3: CURRENCY | AP3: PROVISION VACACIONES | AQ3: PROVISION AGUINALDO
A4: 701910926 | B4: OSCAR JOSUE PEREZ CASCANTE | C4: 701910926 | D4: CR021 | E4: BIPO SANY | F4: STC | G4: SERVICE TECHNICIAN | H4: OPE | I4: OPERATION | J4: P002 | K4: EOR | L4: 73 | M4: EOR STAFF | N4: EOR | O4: EOR | P4: POSTGRADUATE | Q4: POSTGRADUATE | R4: 25/08/2025 | S4: 1750 | T4: 1750 | U4: 171.11 | V4: 300 | W4: 30 | AC4: 221.28 | AD4: 22.51 | AE4: 14.56 | AG4: 603.97 | AH4: 22.51 | AI4: 0 | AJ4: 2251.11 | AK4: 258.35 | AL4: 626.48 | AM4: 1992.76 | AN4: USD | AP4: =SUM(T4:AB4)*3.89% -> 87.568179 | AQ4: =+SUM(T4:AB4)/12 -> 187.5925
S5: TOTAL | T5: =SUM(T4) -> 1750 | U5: =SUM(U4) -> 171.11 | V5: =SUM(V4) -> 300 | W5: =SUM(W4) -> 30 | X5: =SUM(X4) -> 0 | Y5: =SUM(Y4) -> 0 | Z5: =SUM(Z4) -> 0 | AA5: =SUM(AA4) -> 0 | ... AM5: =SUM(AM4) -> 1992.76
