Workbook

Sheet InvoiceDetails
C1: COST REPORT
AI2: EMPLOYER COST | AO2: OTHER EMPLOYER COST | AW2: TOTALS
A3: EMPLOYEE CODE | B3: EE RF WID | C3: NAME | D3: Onboarding Date | E3: Offboarding Date | F3: EE Status (onboarding/active/offboarding) | G3: Country | H3: Customer Name | I3: Customer ID | J3: Payroll Month | K3: Service Type / Invoice Type | L3: ER SS rate % | M3: SALARY | N3: Rectroactive payment/Plus Compensation | O3: "Sick" Leave | P3: Alloawance 1 (Car Allowance) | Q3: Unused Holidays | R3: Overtime | S3: Bonus/Commission | T3: Deduction or Gross Amount adjustments prevous month | U3: Alloawance 2 (Mobile & Internet Allowance) | V3: Food allowance | W3: Alloawance 3 (Home/Remote work allowance) | X3: Alloawance 4 (Other allowances) | Y3: Holidays | Z3: Sign-on Bonus | AA3: Transport allowance | AB3: Wellness Allowance | AC3: On Call/ Plus Disponibilidad | AD3: Severance Pay (Taxable) | AE3: Lieu of Notice | AF3: Paternity/ Maternity leave | AG3: PAYMENTS | AI3: BASIC | AJ3: X100 - APORTE SEG SOCIAL EMPLEADOR | AK3: X200 - APORTE INS EMPLEADOR | AL3: 13TH MONTH (AGUINALDO) | AM3: TOTAL | AO3: OTHER | AP3: OTHER | AQ3: OTHER | AR3: OTHER | AS3: HEALT INSURANCE | AT3: EXPENSES REIMBURSEMENT | AU3: TOTAL | AW3: TOTAL EMPLOYEE COST | AX3: FEE | AY3: BANKING TAX | AZ3: TOTAL | BA3: EXCHANGE RATE | BB3: TOTAL EMPLOYEE COST USD | BC3: FEE USD | BD3: TOTAL USD
A4: =rpt_InformeNominaMes!A4 -> 206860207 | B4: 3976 | C4: =rpt_InformeNominaMes!B4 -> JOSE ROBERTO AGUILAR BARRANTES | D4: =+rpt_InformeNominaMes!R4 -> 11/03/2024 | F4: Onboarding | G4: Costa Rica | H4: Aluminati Network Group Limited | I4: 567 | J4: 46143 | K4: Monthly Payroll | L4: 0.2783 | M4: =rpt_InformeNominaMes!T4 -> 1681000 | N4: 0 | O4: 0 | P4: 0 | Q4: 0 | R4: =+rpt_InformeNominaMes!Y4 -> 0 | S4: =+rpt_InformeNominaMes!W4 -> 0 | T4: 0 | U4: =+rpt_InformeNominaMes!V4 -> 0 | V4: 0 | W4: 0 | X4: =+rpt_InformeNominaMes!X4 -> 0 | Y4: =+rpt_InformeNominaMes!Z4 -> 0 | Z4: 0 | AA4: =+rpt_InformeNominaMes!U4 -> 0 | AB4: 0 | AC4: 0 | AD4: 0 | AE4: 0 | AF4: 0 | AG4: =+SUM($M4:$AF4) -> 1681000 | AI4: =rpt_InformeNominaMes!S4 -> 1681000 | AJ4: =+rpt_InformeNominaMes!AE4 -> 451012.3 | AK4: =+rpt_InformeNominaMes!AF4 -> 16810 | AL4: =+rpt_InformeNominaMes!AN4 -> 140083.33 | AM4: =SUM($AJ4:$AL4) -> 607905.63 | AO4: 0 | AP4: 0 | AQ4: 0 | AR4: 0 | AS4: 0 | AT4: 0 | AU4: =SUM($AO4:$AT4) -> 0 | AW4: =SUM(AG4,AM4,AU4,AY4) -> 2299955.6 | AX4: =135*BA4 -> 59670 | AY4: =25*BA4 -> 11050 | AZ4: =AW4+AX4 -> 2359625.6 | BA4: 442 | BB4: =ROUND($AW4/$BA4,2) -> 5203.52 | BC4: =+AX4/BA4 -> 135 | BD4: =SUM($BB4:$BC4) -> 5338.52 | BE4: =VLOOKUP(A4,rpt_InformeNominaMes!A$4:E$16,5,0) -> ANGL RF | BF4: 135
A5: =rpt_InformeNominaMes!A5 -> 112280205 | B5: 2461 | C5: =rpt_InformeNominaMes!B5 -> TATIANA ARAYA POCHET | D5: =+rpt_InformeNominaMes!R5 -> 17/08/2023 | F5: Onboarding | G5: Costa Rica | H5: Czarnikow Group Limited | I5: 635 | J5: 46143 | K5: Monthly Payroll | L5: 0.2783 | M5: =rpt_InformeNominaMes!T5 -> 8823 | N5: 0 | O5: 0 | P5: 0 | Q5: 0 | R5: =+rpt_InformeNominaMes!Y5 -> 0 | S5: =+rpt_InformeNominaMes!W5 -> 0 | T5: 0 | U5: =+rpt_InformeNominaMes!V5 -> 0 | V5: 0 | W5: 0 | X5: =+rpt_InformeNominaMes!X5 -> 0 | Y5: =+rpt_InformeNominaMes!Z5 -> 0 | Z5: 0 | AA5: =+rpt_InformeNominaMes!U5 -> 0 | AB5: 0 | AC5: 0 | AD5: 0 | AE5: 0 | AF5: 0 | AG5: =+SUM($M5:$AF5) -> 8823 | AI5: =rpt_InformeNominaMes!S5 -> 8823 | AJ5: =+rpt_InformeNominaMes!AE5 -> 2367.21 | AK5: =+rpt_InformeNominaMes!AF5 -> 88.23 | AL5: =+rpt_InformeNominaMes!AN5 -> 735.25 | AM5: =SUM($AJ5:$AL5) -> 3190.69 | AO5: 0 | AP5: 0 | AQ5: 0 | AR5: 0 | AS5: 0 | AT5: 0 | AU5: =SUM($AO5:$AT5) -> 0 | AW5: =SUM(AG5,AM5,AU5,AY5) -> 12038.69 | AX5: 135 | AY5: =25*BA5 -> 25 | AZ5: =AW5+AX5 -> 12173.69 | BA5: 1 | BB5: =ROUND($AW5/$BA5,2) -> 12038.69 | BC5: =+AX5/BA5 -> 135 | BD5: =SUM($BB5:$BC5) -> 12173.69 | BE5: =VLOOKUP(A5,rpt_InformeNominaMes!A$4:E$16,5,0) -> CZARNIKOW | BF5: 135
A6: =rpt_InformeNominaMes!A6 -> 207170459 | B6: 4438 | C6: =rpt_InformeNominaMes!B6 -> SHERYL GERTRUDIS CAMBRONERO ESTRADA | D6: =+rpt_InformeNominaMes!R6 -> 01/05/2024 | F6: Onboarding | G6: Costa Rica | H6: Flores & Pelaez-Prada PLLC | I6: 1352 | J6: 46143 | K6: Monthly Payroll | L6: 0.2783 | M6: =rpt_InformeNominaMes!T6 -> 880501 | N6: 0 | O6: 0 | P6: 0 | Q6: 0 | R6: =+rpt_InformeNominaMes!Y6 -> 0 | S6: =+rpt_InformeNominaMes!W6 -> 0 | T6: 0 | U6: =+rpt_InformeNominaMes!V6 -> 0 | V6: 0 | W6: 0 | X6: =+rpt_InformeNominaMes!X6 -> 0 | Y6: =+rpt_InformeNominaMes!Z6 -> 0 | Z6: 0 | AA6: =+rpt_InformeNominaMes!U6 -> 0 | AB6: 0 | AC6: 0 | AD6: 0 | AE6: 0 | AF6: 0 | AG6: =+SUM($M6:$AF6) -> 880501 | AI6: =rpt_InformeNominaMes!S6 -> 880501 | AJ6: =+rpt_InformeNominaMes!AE6 -> 236238.42 | AK6: =+rpt_InformeNominaMes!AF6 -> 8805.01 | AL6: =+rpt_InformeNominaMes!AN6 -> 73375.083 | AM6: =SUM($AJ6:$AL6) -> 318418.51 | AO6: 0 | AP6: 0 | AQ6: 0 | AR6: 0 | AS6: 0 | AT6: 0 | AU6: =SUM($AO6:$AT6) -> 0 | AW6: =SUM(AG6,AM6,AU6,AY6) -> 1209969.5 | AX6: =135*BA6 -> 59670 | AY6: =25*BA6 -> 11050 | AZ6: =AW6+AX6 -> 1269639.5 | BA6: 442 | BB6: =ROUND($AW6/$BA6,2) -> 2737.49 | BC6: =+AX6/BA6 -> 135 | BD6: =SUM($BB6:$BC6) -> 2872.49 | BE6: =VLOOKUP(A6,rpt_InformeNominaMes!A$4:E$16,5,0) -> FLORES & PELAEZ-PRADA PLLC | BF6: 135
A7: =rpt_InformeNominaMes!A7 -> 118530679 | B7: 0 | C7: =rpt_InformeNominaMes!B7 -> YILLARY KARINA ELLIS PETERS | D7: =+rpt_InformeNominaMes!R7 -> 16/02/2026 | F7: Onboarding | G7: Costa Rica | H7: Uptown Moose, LLC | I7: 0 | J7: 46143 | K7: Monthly Payroll | L7: 0.2783 | M7: =rpt_InformeNominaMes!T7 -> 878400 | N7: 0 | O7: 0 | P7: 0 | Q7: 0 | R7: =+rpt_InformeNominaMes!Y7 -> 0 | S7: =+rpt_InformeNominaMes!W7 -> 0 | T7: 0 | U7: =+rpt_InformeNominaMes!V7 -> 0 | V7: 0 | W7: 0 | X7: =+rpt_InformeNominaMes!X7 -> 0 | Y7: =+rpt_InformeNominaMes!Z7 -> 0 | Z7: 0 | AA7: =+rpt_InformeNominaMes!U7 -> 0 | AB7: 0 | AC7: 0 | AD7: 0 | AE7: 0 | AF7: 0 | AG7: =+SUM($M7:$AF7) -> 878400 | AI7: =rpt_InformeNominaMes!S7 -> 878400 | AJ7: =+rpt_InformeNominaMes!AE7 -> 235674.72 | AK7: =+rpt_InformeNominaMes!AF7 -> 8784 | AL7: =+rpt_InformeNominaMes!AN7 -> 73200 | AM7: =SUM($AJ7:$AL7) -> 317658.72 | AO7: 0 | AP7: 0 | AQ7: 0 | AR7: 0 | AS7: 0 | AT7: 0 | AU7: =SUM($AO7:$AT7) -> 0 | AW7: =SUM(AG7,AM7,AU7,AY7) -> 1207108.7 | AX7: =135*BA7 -> 59670 | AY7: =25*BA7 -> 11050 | AZ7: =AW7+AX7 -> 1266778.7 | BA7: 442 | BB7: =ROUND($AW7/$BA7,2) -> 2731.02 | BC7: =+AX7/BA7 -> 135 | BD7: =SUM($BB7:$BC7) -> 2866.02 | BE7: =VLOOKUP(A7,rpt_InformeNominaMes!A$4:E$16,5,0) -> UPTOWN MOOSE LLC (RF) | BF7: 135
A8: =rpt_InformeNominaMes!A8 -> 112850849 | B8: 7709 | C8: =rpt_InformeNominaMes!B8 -> BERNAL FALLAS BARBOZA | D8: =+rpt_InformeNominaMes!R8 -> 01/03/2025 | F8: Onboarding | G8: Costa Rica | H8: Berkheimer Enterprises LLC - DBA "Beneficial Talent Source | I8: 2119 | J8: 46143 | K8: Monthly Payroll | L8: 0.2783 | M8: =rpt_InformeNominaMes!T8 -> 6500 | N8: 0 | O8: 0 | P8: 0 | Q8: 0 | R8: =+rpt_InformeNominaMes!Y8 -> 0 | S8: =+rpt_InformeNominaMes!W8 -> 0 | T8: 0 | U8: =+rpt_InformeNominaMes!V8 -> 0 | V8: 0 | W8: 0 | X8: =+rpt_InformeNominaMes!X8 -> 0 | Y8: =+rpt_InformeNominaMes!Z8 -> 0 | Z8: 0 | AA8: =+rpt_InformeNominaMes!U8 -> 0 | AB8: 0 | AC8: 0 | AD8: 0 | AE8: 0 | AF8: 0 | AG8: =+SUM($M8:$AF8) -> 6500 | AI8: =rpt_InformeNominaMes!S8 -> 6500 | AJ8: =+rpt_InformeNominaMes!AE8 -> 1743.95 | AK8: =+rpt_InformeNominaMes!AF8 -> 65 | AL8: =+rpt_InformeNominaMes!AN8 -> 541.66667 | AM8: =SUM($AJ8:$AL8) -> 2350.6167 | AO8: 0 | AP8: 0 | AQ8: 0 | AR8: 0 | AS8: 0 | AT8: 0 | AU8: =SUM($AO8:$AT8) -> 0 | AW8: =SUM(AG8,AM8,AU8,AY8) -> 8875.6167 | AX8: =135*BA8 -> 135 | AY8: =25*BA8 -> 25 | AZ8: =AW8+AX8 -> 9010.6167 | BA8: 1 | BB8: =ROUND($AW8/$BA8,2) -> 8875.62 | BC8: =+AX8/BA8 -> 135 | BD8: =SUM($BB8:$BC8) -> 9010.62 | BE8: =VLOOKUP(A8,rpt_InformeNominaMes!A$4:E$16,5,0) -> REMOFIRST - BERKHEIMER ENTERPRISES LLC | BF8: 135
A9: =rpt_InformeNominaMes!A9 -> 114860203 | B9: 2114 | C9: =rpt_InformeNominaMes!B9 -> PRISCILLA GRACE POLSON GIESBRECHT | D9: =+rpt_InformeNominaMes!R9 -> 16/06/2023 | F9: Onboarding | G9: Costa Rica | H9: Aluminati Network Group Limited | I9: 567 | J9: 46143 | K9: Monthly Payroll | L9: 0.2783 | M9: =rpt_InformeNominaMes!T9 -> 1681000 | N9: 0 | O9: 0 | P9: 0 | Q9: 0 | R9: =+rpt_InformeNominaMes!Y9 -> 0 | S9: =+rpt_InformeNominaMes!W9 -> 0 | T9: 0 | U9: =+rpt_InformeNominaMes!V9 -> 0 | V9: 0 | W9: 0 | X9: =+rpt_InformeNominaMes!X9 -> 0 | Y9: =+rpt_InformeNominaMes!Z9 -> 0 | Z9: 0 | AA9: =+rpt_InformeNominaMes!U9 -> 0 | AB9: 0 | AC9: 0 | AD9: 0 | AE9: 0 | AF9: 0 | AG9: =+SUM($M9:$AF9) -> 1681000 | AI9: =rpt_InformeNominaMes!S9 -> 1681000 | AJ9: =+rpt_InformeNominaMes!AE9 -> 451012.3 | AK9: =+rpt_InformeNominaMes!AF9 -> 16810 | AL9: =+rpt_InformeNominaMes!AN9 -> 140083.33 | AM9: =SUM($AJ9:$AL9) -> 607905.63 | AO9: 0 | AP9: 0 | AQ9: 0 | AR9: 0 | AS9: 0 | AT9: 0 | AU9: =SUM($AO9:$AT9) -> 0 | AW9: =SUM(AG9,AM9,AU9,AY9) -> 2299955.6 | AX9: =135*BA9 -> 59670 | AY9: =25*BA9 -> 11050 | AZ9: =AW9+AX9 -> 2359625.6 | BA9: 442 | BB9: =ROUND($AW9/$BA9,2) -> 5203.52 | BC9: =+AX9/BA9 -> 135 | BD9: =SUM($BB9:$BC9) -> 5338.52 | BE9: =VLOOKUP(A9,rpt_InformeNominaMes!A$4:E$16,5,0) -> ANGL RF | BF9: 135
A10: =rpt_InformeNominaMes!A10 -> 503990169 | B10: 2084 | C10: =rpt_InformeNominaMes!B10 -> JONATHAN ALONSO SALAZAR GARCIA | D10: =+rpt_InformeNominaMes!R10 -> 21/05/2023 | F10: Onboarding | G10: Costa Rica | H10: Starlight Software Solutions | I10: 563 | J10: 46143 | K10: Monthly Payroll | L10: 0.2783 | M10: =rpt_InformeNominaMes!T10 -> 4167 | N10: 0 | O10: 0 | P10: 0 | Q10: 0 | R10: =+rpt_InformeNominaMes!Y10 -> 0 | S10: =+rpt_InformeNominaMes!W10 -> 0 | T10: 0 | U10: =+rpt_InformeNominaMes!V10 -> 0 | V10: 0 | W10: 0 | X10: =+rpt_InformeNominaMes!X10 -> 0 | Y10: =+rpt_InformeNominaMes!Z10 -> 0 | Z10: 0 | AA10: =+rpt_InformeNominaMes!U10 -> 0 | AB10: 0 | AC10: 0 | AD10: 0 | AE10: 0 | AF10: 0 | AG10: =+SUM($M10:$AF10) -> 4167 | AI10: =rpt_InformeNominaMes!S10 -> 4167 | AJ10: =+rpt_InformeNominaMes!AE10 -> 1118.01 | AK10: =+rpt_InformeNominaMes!AF10 -> 41.67 | AL10: =+rpt_InformeNominaMes!AN10 -> 347.25 | AM10: =SUM($AJ10:$AL10) -> 1506.93 | AO10: 0 | AP10: 0 | AQ10: 0 | AR10: 0 | AS10: 0 | AT10: 0 | AU10: =SUM($AO10:$AT10) -> 0 | AW10: =SUM(AG10,AM10,AU10,AY10) -> 5698.93 | AX10: 135 | AY10: =25*BA10 -> 25 | AZ10: =AW10+AX10 -> 5833.93 | BA10: 1 | BB10: =ROUND($AW10/$BA10,2) -> 5698.93 | BC10: =+AX10/BA10 -> 135 | BD10: =SUM($BB10:$BC10) -> 5833.93 | BE10: =VLOOKUP(A10,rpt_InformeNominaMes!A$4:E$16,5,0) -> SSS - RF | BF10: 135
A11: =rpt_InformeNominaMes!A11 -> 117030514 | B11: 0 | C11: =rpt_InformeNominaMes!B11 -> VIRGINIA PAOLA SALAZAR HERNANDEZ | D11: =+rpt_InformeNominaMes!R11 -> 25/02/2026 | F11: Onboarding | G11: Costa Rica | H11: Suol Innovations Ltd | I11: 0 | J11: 46143 | K11: Monthly Payroll | L11: 0.2783 | M11: =rpt_InformeNominaMes!T11 -> 1250000 | N11: 0 | O11: 0 | P11: 0 | Q11: 0 | R11: =+rpt_InformeNominaMes!Y11 -> 0 | S11: =+rpt_InformeNominaMes!W11 -> 0 | T11: 0 | U11: =+rpt_InformeNominaMes!V11 -> 0 | V11: 0 | W11: 0 | X11: =+rpt_InformeNominaMes!X11 -> 0 | Y11: =+rpt_InformeNominaMes!Z11 -> 0 | Z11: 0 | AA11: =+rpt_InformeNominaMes!U11 -> 0 | AB11: 0 | AC11: 0 | AD11: 0 | AE11: 0 | AF11: 0 | AG11: =+SUM($M11:$AF11) -> 1250000 | AI11: =rpt_InformeNominaMes!S11 -> 1250000 | AJ11: =+rpt_InformeNominaMes!AE11 -> 335375 | AK11: =+rpt_InformeNominaMes!AF11 -> 12500 | AL11: =+rpt_InformeNominaMes!AN11 -> 104166.67 | AM11: =SUM($AJ11:$AL11) -> 452041.67 | AO11: 0 | AP11: 0 | AQ11: 0 | AR11: 0 | AS11: 0 | AT11: 0 | AU11: =SUM($AO11:$AT11) -> 0 | AW11: =SUM(AG11,AM11,AU11,AY11) -> 1713091.7 | AX11: =135*BA11 -> 59670 | AY11: =25*BA11 -> 11050 | AZ11: =AW11+AX11 -> 1772761.7 | BA11: 442 | BB11: =ROUND($AW11/$BA11,2) -> 3875.77 | BC11: =+AX11/BA11 -> 135 | BD11: =SUM($BB11:$BC11) -> 4010.77 | BE11: =VLOOKUP(A11,rpt_InformeNominaMes!A$4:E$16,5,0) -> SUOL INNOVATIONS LTD (RF) | BF11: 135
A12: =rpt_InformeNominaMes!A12 -> 115630104 | B12: 10540 | C12: =rpt_InformeNominaMes!B12 -> GILBERTO ESTEBAN SOLANO MENDEZ | D12: =+rpt_InformeNominaMes!R12 -> 01/07/2025 | F12: Onboarding | G12: Costa Rica | H12: Berkheimer Enterprises LLC - DBA "Beneficial Talent Source | I12: 2119 | J12: 46143 | K12: Monthly Payroll | L12: 0.2783 | M12: =rpt_InformeNominaMes!T12 -> 2540768 | N12: 0 | O12: 0 | P12: 0 | Q12: 0 | R12: =+rpt_InformeNominaMes!Y12 -> 0 | S12: =+rpt_InformeNominaMes!W12 -> 0 | T12: 0 | U12: =+rpt_InformeNominaMes!V12 -> 0 | V12: 0 | W12: 0 | X12: =+rpt_InformeNominaMes!X12 -> 0 | Y12: =+rpt_InformeNominaMes!Z12 -> 0 | Z12: 0 | AA12: =+rpt_InformeNominaMes!U12 -> 0 | AB12: 0 | AC12: 0 | AD12: 0 | AE12: 0 | AF12: 0 | AG12: =+SUM($M12:$AF12) -> 2540768 | AI12: =rpt_InformeNominaMes!S12 -> 2540768 | AJ12: =+rpt_InformeNominaMes!AE12 -> 681688.05 | AK12: =+rpt_InformeNominaMes!AF12 -> 25407.68 | AL12: =+rpt_InformeNominaMes!AN12 -> 211730.67 | AM12: =SUM($AJ12:$AL12) -> 918826.4 | AO12: 0 | AP12: 0 | AQ12: 0 | AR12: 0 | AS12: 0 | AT12: 0 | AU12: =SUM($AO12:$AT12) -> 0 | AW12: =SUM(AG12,AM12,AU12,AY12) -> 3470644.4 | AX12: =135*BA12 -> 59670 | AY12: =25*BA12 -> 11050 | AZ12: =AW12+AX12 -> 3530314.4 | BA12: 442 | BB12: =ROUND($AW12/$BA12,2) -> 7852.14 | BC12: =+AX12/BA12 -> 135 | BD12: =SUM($BB12:$BC12) -> 7987.14 | BE12: =VLOOKUP(A12,rpt_InformeNominaMes!A$4:E$16,5,0) -> REMOFIRST - BERKHEIMER ENTERPRISES LLC | BF12: 135
A13: =rpt_InformeNominaMes!A13 -> 603250181 | B13: 10748 | C13: =rpt_InformeNominaMes!B13 -> ANGEL ALBERTO TORRES GONZALEZ | D13: =+rpt_InformeNominaMes!R13 -> 07/07/2025 | F13: Onboarding | G13: Costa Rica | H13: Skellig Automation US LLC | I13: 3189 | J13: 46143 | K13: Monthly Payroll | L13: 0.2783 | M13: =rpt_InformeNominaMes!T13 -> 10167 | N13: 0 | O13: 0 | P13: 0 | Q13: 0 | R13: =+rpt_InformeNominaMes!Y13 -> 879.8 | S13: =+rpt_InformeNominaMes!W13 -> 0 | T13: 0 | U13: =+rpt_InformeNominaMes!V13 -> 0 | V13: 0 | W13: 0 | X13: =+rpt_InformeNominaMes!X13 -> 0 | Y13: =+rpt_InformeNominaMes!Z13 -> 0 | Z13: 0 | AA13: =+rpt_InformeNominaMes!U13 -> 0 | AB13: 0 | AC13: 0 | AD13: 0 | AE13: 0 | AF13: 0 | AG13: =+SUM($M13:$AF13) -> 11046.8 | AI13: =rpt_InformeNominaMes!S13 -> 10167 | AJ13: =+rpt_InformeNominaMes!AE13 -> 2936.83 | AK13: =+rpt_InformeNominaMes!AF13 -> 110.47 | AL13: =+rpt_InformeNominaMes!AN13 -> 920.56667 | AM13: =SUM($AJ13:$AL13) -> 3967.8667 | AO13: 0 | AP13: 0 | AQ13: 0 | AR13: 0 | AS13: 0 | AT13: 0 | AU13: =SUM($AO13:$AT13) -> 0 | AW13: =SUM(AG13,AM13,AU13,AY13) -> 15039.667 | AX13: =135*BA13 -> 135 | AY13: =25*BA13 -> 25 | AZ13: =AW13+AX13 -> 15174.667 | BA13: 1 | BB13: =ROUND($AW13/$BA13,2) -> 15039.67 | BC13: =+AX13/BA13 -> 135 | BD13: =SUM($BB13:$BC13) -> 15174.67 | BE13: =VLOOKUP(A13,rpt_InformeNominaMes!A$4:E$16,5,0) -> REMOFIRST - SKELLIG AUTOMATION US LLC | BF13: 135
A14: =rpt_InformeNominaMes!A14 -> 110930288 | B14: 10620 | C14: =rpt_InformeNominaMes!B14 -> JORGE ESTEBAN VALVERDE ESPINOZA | D14: =+rpt_InformeNominaMes!R14 -> 18/08/2025 | F14: Onboarding | G14: Costa Rica | H14: IPPC Technologies | I14: 3271 | J14: 46143 | K14: Monthly Payroll | L14: 0.2783 | M14: =rpt_InformeNominaMes!T14 -> 9188 | N14: 0 | O14: 0 | P14: 0 | Q14: 0 | R14: =+rpt_InformeNominaMes!Y14 -> 0 | S14: =+rpt_InformeNominaMes!W14 -> 0 | T14: 0 | U14: =+rpt_InformeNominaMes!V14 -> 0 | V14: 0 | W14: 0 | X14: =+rpt_InformeNominaMes!X14 -> 700 | Y14: =+rpt_InformeNominaMes!Z14 -> 0 | Z14: 0 | AA14: =+rpt_InformeNominaMes!U14 -> 0 | AB14: 0 | AC14: 0 | AD14: 0 | AE14: 0 | AF14: 0 | AG14: =+SUM($M14:$AF14) -> 9888 | AI14: =rpt_InformeNominaMes!S14 -> 9188 | AJ14: =+rpt_InformeNominaMes!AE14 -> 2652.95 | AK14: =+rpt_InformeNominaMes!AF14 -> 98.88 | AL14: =+rpt_InformeNominaMes!AN14 -> 824 | AM14: =SUM($AJ14:$AL14) -> 3575.83 | AO14: 0 | AP14: 0 | AQ14: 0 | AR14: 0 | AS14: 0 | AT14: 0 | AU14: =SUM($AO14:$AT14) -> 0 | AW14: =SUM(AG14,AM14,AU14,AY14) -> 13488.83 | AX14: 135 | AY14: =25*BA14 -> 25 | AZ14: =AW14+AX14 -> 13623.83 | BA14: 1 | BB14: =ROUND($AW14/$BA14,2) -> 13488.83 | BC14: =+AX14/BA14 -> 135 | BD14: =SUM($BB14:$BC14) -> 13623.83 | BE14: =VLOOKUP(A14,rpt_InformeNominaMes!A$4:E$16,5,0) -> REMOFIRST-IPPC TECHNOLOGIES | BF14: 135
A15: =rpt_InformeNominaMes!A15 -> 114980416 | B15: 0 | C15: =rpt_InformeNominaMes!B15 -> ELIZABETH STEPHANIE VARGAS SALAZAR | D15: =+rpt_InformeNominaMes!R15 -> 09/02/2026 | F15: Onboarding | G15: Costa Rica | H15: Comrise, Inc. | I15: 0 | J15: 46143 | K15: Monthly Payroll | L15: 0.2783 | M15: =rpt_InformeNominaMes!T15 -> 989384 | N15: 0 | O15: 0 | P15: 0 | Q15: 0 | R15: =+rpt_InformeNominaMes!Y15 -> 0 | S15: =+rpt_InformeNominaMes!W15 -> 0 | T15: 0 | U15: =+rpt_InformeNominaMes!V15 -> 0 | V15: 0 | W15: 0 | X15: =+rpt_InformeNominaMes!X15 -> 0 | Y15: =+rpt_InformeNominaMes!Z15 -> 0 | Z15: 0 | AA15: =+rpt_InformeNominaMes!U15 -> 0 | AB15: 0 | AC15: 0 | AD15: 0 | AE15: 0 | AF15: 0 | AG15: =+SUM($M15:$AF15) -> 989384 | AI15: =rpt_InformeNominaMes!S15 -> 989384 | AJ15: =+rpt_InformeNominaMes!AE15 -> 265451.73 | AK15: =+rpt_InformeNominaMes!AF15 -> 9893.84 | AL15: =+rpt_InformeNominaMes!AN15 -> 82448.667 | AM15: =SUM($AJ15:$AL15) -> 357794.24 | AO15: 0 | AP15: 0 | AQ15: 0 | AR15: 0 | AS15: 0 | AT15: 0 | AU15: =SUM($AO15:$AT15) -> 0 | AW15: =SUM(AG15,AM15,AU15,AY15) -> 1358228.2 | AX15: =135*BA15 -> 59670 | AY15: =25*BA15 -> 11050 | AZ15: =AW15+AX15 -> 1417898.2 | BA15: 442 | BB15: =ROUND($AW15/$BA15,2) -> 3072.91 | BC15: =+AX15/BA15 -> 135 | BD15: =SUM($BB15:$BC15) -> 3207.91 | BE15: =VLOOKUP(A15,rpt_InformeNominaMes!A$4:E$16,5,0) -> COMRISE INC (RF) | BF15: 135
A16: =rpt_InformeNominaMes!A16 -> 604810574 | B16: 11763 | C16: =rpt_InformeNominaMes!B16 -> GEANINA VILLALOBOS MOLINA | D16: =+rpt_InformeNominaMes!R16 -> 01/09/2025 | F16: Onboarding | G16: Costa Rica | H16: AIS Ventures LLC | I16: 3948 | J16: 46143 | K16: Monthly Payroll | L16: 0.2783 | M16: =rpt_InformeNominaMes!T16 -> 1000000 | N16: 0 | O16: 0 | P16: 0 | Q16: 0 | R16: =+rpt_InformeNominaMes!Y16 -> 0 | S16: =+rpt_InformeNominaMes!W16 -> 0 | T16: 0 | U16: =+rpt_InformeNominaMes!V16 -> 0 | V16: 0 | W16: 0 | X16: =+rpt_InformeNominaMes!X16 -> 0 | Y16: =+rpt_InformeNominaMes!Z16 -> 0 | Z16: 0 | AA16: =+rpt_InformeNominaMes!U16 -> 0 | AB16: 0 | AC16: 0 | AD16: 0 | AE16: 0 | AF16: 0 | AG16: =+SUM($M16:$AF16) -> 1000000 | AI16: =rpt_InformeNominaMes!S16 -> 1000000 | AJ16: =+rpt_InformeNominaMes!AE16 -> 268300 | AK16: =+rpt_InformeNominaMes!AF16 -> 10000 | AL16: =+rpt_InformeNominaMes!AN16 -> 83333.333 | AM16: =SUM($AJ16:$AL16) -> 361633.33 | AO16: 0 | AP16: 0 | AQ16: 0 | AR16: 0 | AS16: 0 | AT16: 0 | AU16: =SUM($AO16:$AT16) -> 0 | AW16: =SUM(AG16,AM16,AU16,AY16) -> 1372683.3 | AX16: =135*BA16 -> 59670 | AY16: =25*BA16 -> 11050 | AZ16: =AW16+AX16 -> 1432353.3 | BA16: 442 | BB16: =ROUND($AW16/$BA16,2) -> 3105.62 | BC16: =+AX16/BA16 -> 135 | BD16: =SUM($BB16:$BC16) -> 3240.62 | BE16: =VLOOKUP(A16,rpt_InformeNominaMes!A$4:E$16,5,0) -> AIS VENTURES LLC (RF) | BF16: 135
H17: TOTALES | M17: =+SUM(M4:M16) -> 10939898 | N17: =+SUM(N4:N16) -> 0 | O17: =+SUM(O4:O16) -> 0 | P17: =+SUM(P4:P16) -> 0 | Q17: =+SUM(Q4:Q16) -> 0 | R17: =+SUM(R4:R16) -> 879.8 | S17: =+SUM(S4:S16) -> 0 | T17: =+SUM(T4:T16) -> 0 | ... AG17: =+SUM(AG4:AG16) -> 10941478 | AI17: TOTAL | AJ17: =+SUM(AJ4:AJ16) -> 2935571.5 | AK17: =+SUM(AK4:AK16) -> 109414.78 | AL17: =+SUM(AL4:AL16) -> 911789.82 | AM17: =+SUM(AM4:AM16) -> 3956776.1 | AO17: =+SUM(AO4:AO16) -> 0 | AP17: =+SUM(AP4:AP16) -> 0 | AQ17: =+SUM(AQ4:AQ16) -> 0 | AR17: =+SUM(AR4:AR16) -> 0 | AS17: =+SUM(AS4:AS16) -> 0 | AT17: =+SUM(AT4:AT16) -> 0 | AU17: =+SUM(AU4:AU16) -> 0 | AW17: =+SUM(AW4:AW16) -> 14986779 | AX17: =+SUM(AX4:AX16) -> 478035 | AY17: =+SUM(AY4:AY16) -> 88525 | AZ17: =+SUM(AZ4:AZ16) -> 15464814 | BB17: =+SUM(BB4:BB16) -> 88923.73 | BC17: =+SUM(BC4:BC16) -> 1755 | BD17: =+SUM(BD4:BD16) -> 90678.73
A19: Payroll Adjustments (Previous months) Breakdown
A20: EMPLOYEE CODE | B20: EE RF WID | C20: NAME | D20: Onboarding Date | E20: Offboarding Date | F20: EE Status (onboarding/active/offboarding) | G20: Country | H20: Customer Name | I20: Customer ID | J20: Payroll Month | K20: Service Type / Invoice Type | L20: ER SS rate % | M20: SALARY | N20: Rectroactive payment/Plus Compensation | O20: "Sick" Leave | P20: Alloawance 1 (Car Allowance) | Q20: Unused Holidays | R20: Overtime | S20: Bonus/Commission | T20: Deduction or Gross Amount adjustments prevous month | U20: Alloawance 2 (Mobile & Internet Allowance) | V20: Food allowance | W20: Alloawance 3 (Home/Remote work allowance) | X20: Alloawance 4 (Other allowances) | Z20: Sign-on Bonus | AA20: Transport allowance | AB20: Wellness Allowance | AC20: On Call/ Plus Disponibilidad | AD20: Severance Pay (Taxable) | AE20: Lieu of Notice | AF20: Paternity/ Maternity leave | AG20: PAYMENTS | AJ20: HEALTH COST | AL20: 13TH SALARY | AM20: TOTAL | AO20: EXPENSES | AP20: HEALTH INSURANCE | AQ20: MEDICAL TEST | AR20: LEAVE PAID REFOUND | AS20: PARKING COST | AU20: TOTAL | AW20: TOTAL EMPLOYEE COST | AX20: FEE | AY20: BANKING TAX | AZ20: TOTAL COP | BA20: EXCHANGE RATE | BB20: TOTAL EMPLOYEE COST USD | BC20: FEE USD | BD20: TOTAL USD

Sheet rpt_InformeNominaMes
B1: Informe de Nómina Movimiento Liquidado MLQ , Nómina: ('ME01') Periodo: ('20260505') -
A3: EMPLEADO | B3: NOMBRE COMPLETO | C3: DOCUMENTO IDENTIDAD | D3: CCOSTO | E3: DESC.CCOSTO | F3: OFICIO | G3: DESC. OFICIO | H3: AREA | I3: DESC.AREA | J3: PROYECTO | K3: DESC.PROYECTO | L3: GRUPO | M3: DESC.GRUPO | N3: DPTO | O3: DESC.DEPTO | P3: NIVEL | Q3: DESC.NIVEL | R3: FECHA ANTIGUEDAD | S3: SALARIO | T3: A000 - SALARIO ORDINARIO | U3: A023 - AUXILIO DE TRANSPORTE | V3: A024 - AUXILIO DE TELECOMUNICACIONES | W3: A025 - BONO SALARIAL | X3: A028 - AUXILIO DE SALUD | Y3: C001 - HORA EXTRA DIURNA | Z3: G006 - VACACIONES DISFRUTADAS HABILES | AA3: H100 - APORTE SEG SOCIAL | AB3: I100 - APORTE BANCO POPULAR | AC3: R003 - RETENCION EN LA FUENTE | AD3: R004 - RETENCION EN LA FUENTE USD | AE3: X100 - APORTE SEG SOCIAL EMPLEADOR | AF3: X200 - APORTE INS EMPLEADOR | AG3: DEVENGADOS | AH3: DEDUCCIONES | AI3: APORTES DEL EMPLEADOR | AJ3: NETO A PAGAR | AK3: CURRENCY | AM3: PROVISION VACACIONES | AN3: PROVISION AGUINALDO
A4: 206860207 | B4: JOSE ROBERTO AGUILAR BARRANTES | C4: 206860207 | D4: CR004 | E4: ANGL RF | F4: CSS | G4: CLIENT SERVICE SPECIALIST | H4: OPE | I4: OPERATION | J4: P002 | K4: EOR | L4: 73 | M4: EOR STAFF | N4: EOR | O4: EOR | P4: GRADUATE | Q4: GARDUATE | R4: 11/03/2024 | S4: 1681000 | T4: 1681000 | AA4: 165242.3 | AB4: 16810 | AC4: 92999.9 | AE4: 451012.3 | AF4: 16810 | AG4: 1681000 | AH4: 275052.2 | AI4: 467822.3 | AJ4: 1405947.8 | AK4: CRC | AM4: =SUM(T4:Z4)*3.89% -> 65390.9 | AN4: =+SUM(T4:Z4)/12 -> 140083.33
A5: 112280205 | B5: TATIANA ARAYA POCHET | C5: 112280205 | D5: CR006 | E5: CZARNIKOW | F5: INT | G5: INGREDIENT TRADER | H5: OPE | I5: OPERATION | J5: P002 | K5: EOR | L5: 73 | M5: EOR STAFF | N5: EOR | O5: EOR | P5: POSTGRADUATE | Q5: POSTGRADUATE | R5: 17/08/2023 | S5: 8823 | T5: 8823 | AA5: 867.3 | AB5: 88.23 | AD5: 1137.11 | AE5: 2367.21 | AF5: 88.23 | AG5: 8823 | AH5: 2092.64 | AI5: 2455.44 | AJ5: 6730.36 | AK5: USD | AM5: =SUM(T5:Z5)*3.89% -> 343.2147 | AN5: =+SUM(T5:Z5)/12 -> 735.25
A6: 207170459 | B6: SHERYL GERTRUDIS CAMBRONERO ESTRADA | C6: 207170459 | D6: CR007 | E6: FLORES & PELAEZ-PRADA PLLC | F6: VA | G6: VIRTUAL ASSISTANT | H6: OPE | I6: OPERATION | J6: P002 | K6: EOR | L6: 73 | M6: EOR STAFF | N6: EOR | O6: EOR | P6: GRADUATE | Q6: GARDUATE | R6: 01/05/2024 | S6: 880501 | T6: 880501 | AA6: 86553.25 | AB6: 8805.01 | AE6: 236238.42 | AF6: 8805.01 | AG6: 880501 | AH6: 95358.26 | AI6: 245043.43 | AJ6: 785142.74 | AK6: CRC | AM6: =SUM(T6:Z6)*3.89% -> 34251.489 | AN6: =+SUM(T6:Z6)/12 -> 73375.083
A7: 118530679 | B7: YILLARY KARINA ELLIS PETERS | C7: 118530679 | D7: CR020 | E7: UPTOWN MOOSE LLC (RF) | F7: RCC | G7: REGULATORY COMPLIANCE COORDINATOR | H7: OPE | I7: OPERATION | J7: P002 | K7: EOR | L7: 73 | M7: EOR STAFF | N7: EOR | O7: EOR | P7: POSTGRADUATE | Q7: POSTGRADUATE | R7: 16/02/2026 | S7: 878400 | T7: 878400 | AA7: 86346.72 | AB7: 8784 | AE7: 235674.72 | AF7: 8784 | AG7: 878400 | AH7: 95130.72 | AI7: 244458.72 | AJ7: 783269.28 | AK7: CRC | AM7: =SUM(T7:Z7)*3.89% -> 34169.76 | AN7: =+SUM(T7:Z7)/12 -> 73200
A8: 112850849 | B8: BERNAL FALLAS BARBOZA | C8: 112850849 | D8: CR009 | E8: REMOFIRST - BERKHEIMER ENTERPRISES LLC | F8: SRO | G8: SR. ORACLE DEVELOPER | H8: OPE | I8: OPERATION | J8: P002 | K8: EOR | L8: 73 | M8: EOR STAFF | N8: EOR | O8: EOR | P8: GRADUATE | Q8: GARDUATE | R8: 01/03/2025 | S8: 6500 | T8: 6500 | AA8: 638.95 | AB8: 65 | AD8: 672.51 | AE8: 1743.95 | AF8: 65 | AG8: 6500 | AH8: 1376.46 | AI8: 1808.95 | AJ8: 5123.54 | AK8: USD | AM8: =SUM(T8:Z8)*3.89% -> 252.85 | AN8: =+SUM(T8:Z8)/12 -> 541.66667
A9: 114860203 | B9: PRISCILLA GRACE POLSON GIESBRECHT | C9: 114860203 | D9: CR004 | E9: ANGL RF | F9: CSS | G9: CLIENT SERVICE SPECIALIST | H9: OPE | I9: OPERATION | J9: P002 | K9: EOR | L9: 73 | M9: EOR STAFF | N9: EOR | O9: EOR | P9: POSTGRADUATE | Q9: POSTGRADUATE | R9: 16/06/2023 | S9: 1681000 | T9: 1681000 | AA9: 165242.3 | AB9: 16810 | AC9: 92999.9 | AE9: 451012.3 | AF9: 16810 | AG9: 1681000 | AH9: 275052.2 | AI9: 467822.3 | AJ9: 1405947.8 | AK9: CRC | AM9: =SUM(T9:Z9)*3.89% -> 65390.9 | AN9: =+SUM(T9:Z9)/12 -> 140083.33
A10: 503990169 | B10: JONATHAN ALONSO SALAZAR GARCIA | C10: 503990169 | D10: CR003 | E10: SSS - RF | F10: SDE | G10: SR DEVELOPMENT ENGINEER | H10: OPE | I10: OPERATION | J10: P002 | K10: EOR | L10: 73 | M10: EOR STAFF | N10: EOR | O10: EOR | P10: POSTGRADUATE | Q10: POSTGRADUATE | R10: 21/05/2023 | S10: 4167 | T10: 4167 | AA10: 409.62 | AB10: 41.67 | AD10: 261.07 | AE10: 1118.01 | AF10: 41.67 | AG10: 4167 | AH10: 712.36 | AI10: 1159.68 | AJ10: 3454.64 | AK10: USD | AM10: =SUM(T10:Z10)*3.89% -> 162.0963 | AN10: =+SUM(T10:Z10)/12 -> 347.25
A11: 117030514 | B11: VIRGINIA PAOLA SALAZAR HERNANDEZ | C11: 117030514 | D11: CR016 | E11: SUOL INNOVATIONS LTD (RF) | F11: DOS | G11: DRIVER OPERATIONS SPECIALIST | H11: OPE | I11: OPERATION | J11: P002 | K11: EOR | L11: 73 | M11: EOR STAFF | N11: EOR | O11: EOR | P11: POSTGRADUATE | Q11: POSTGRADUATE | R11: 25/02/2026 | S11: 1250000 | T11: 1250000 | AA11: 122875 | AB11: 12500 | AC11: 33200 | AE11: 335375 | AF11: 12500 | AG11: 1250000 | AH11: 168575 | AI11: 347875 | AJ11: 1081425 | AK11: CRC | AM11: =SUM(T11:Z11)*3.89% -> 48625 | AN11: =+SUM(T11:Z11)/12 -> 104166.67
A12: 115630104 | B12: GILBERTO ESTEBAN SOLANO MENDEZ | C12: 115630104 | D12: CR009 | E12: REMOFIRST - BERKHEIMER ENTERPRISES LLC | F12: QAAE | G12: QA AUTOMATION ENGINEER | H12: OPE | I12: OPERATION | J12: P002 | K12: EOR | L12: 73 | M12: EOR STAFF | N12: EOR | O12: EOR | P12: GRADUATE | Q12: GARDUATE | R12: 01/07/2025 | S12: 2540768 | T12: 2540768 | AA12: 249757.49 | AB12: 25407.68 | AC12: 230803.35 | AE12: 681688.05 | AF12: 25407.68 | AG12: 2540768 | AH12: 505968.52 | AI12: 707095.73 | AJ12: 2034799.5 | AK12: CRC | AM12: =SUM(T12:Z12)*3.89% -> 98835.875 | AN12: =+SUM(T12:Z12)/12 -> 211730.67
A13: 603250181 | B13: ANGEL ALBERTO TORRES GONZALEZ | C13: 603250181 | D13: CR012 | E13: REMOFIRST - SKELLIG AUTOMATION US LLC | F13: SAE | G13: SENIOR AUTOMATION ENGINEER II | H13: OPE | I13: OPERATION | J13: P002 | K13: EOR | L13: 73 | M13: EOR STAFF | N13: EOR | O13: EOR | P13: POSTGRADUATE | Q13: POSTGRADUATE | R13: 07/07/2025 | S13: 10167 | T13: 10167 | Y13: 879.8 | AA13: 1085.9 | AB13: 110.47 | AD13: 1599.48 | AE13: 2936.83 | AF13: 110.47 | AG13: 11046.8 | AH13: 2795.85 | AI13: 3047.3 | AJ13: 8250.95 | AK13: USD | AM13: =SUM(T13:Z13)*3.89% -> 429.72052 | AN13: =+SUM(T13:Z13)/12 -> 920.56667
A14: 110930288 | B14: JORGE ESTEBAN VALVERDE ESPINOZA | C14: 110930288 | D14: CR011 | E14: REMOFIRST-IPPC TECHNOLOGIES | F14: TPM | G14: TECHNICAL PROGRAM MANAGER | H14: OPE | I14: OPERATION | J14: P002 | K14: EOR | L14: 73 | M14: EOR STAFF | N14: EOR | O14: EOR | P14: POSTGRADUATE | Q14: POSTGRADUATE | R14: 18/08/2025 | S14: 9188 | T14: 9188 | X14: 700 | AA14: 971.99 | AB14: 98.88 | AD14: 1350.11 | AE14: 2652.95 | AF14: 98.88 | AG14: 9888 | AH14: 2420.98 | AI14: 2751.83 | AJ14: 7467.02 | AK14: USD | AM14: =SUM(T14:Z14)*3.89% -> 384.6432 | AN14: =+SUM(T14:Z14)/12 -> 824
A15: 114980416 | B15: ELIZABETH STEPHANIE VARGAS SALAZAR | C15: 114980416 | D15: CR019 | E15: COMRISE INC (RF) | F15: RLGS | G15: RECRUITER/LEADS GEN SPECIALIST | H15: OPE | I15: OPERATION | J15: P002 | K15: EOR | L15: 73 | M15: EOR STAFF | N15: EOR | O15: EOR | P15: POSTGRADUATE | Q15: POSTGRADUATE | R15: 09/02/2026 | S15: 989384 | T15: 989384 | AA15: 97256.45 | AB15: 9893.84 | AC15: 7138.4 | AE15: 265451.73 | AF15: 9893.84 | AG15: 989384 | AH15: 114288.69 | AI15: 275345.57 | AJ15: 875095.31 | AK15: CRC | AM15: =SUM(T15:Z15)*3.89% -> 38487.038 | AN15: =+SUM(T15:Z15)/12 -> 82448.667
A16: 604810574 | B16: GEANINA VILLALOBOS MOLINA | C16: 604810574 | D16: CR015 | E16: AIS VENTURES LLC (RF) | F16: LPA | G16: LOAN PROCESSING ASSISTANT | H16: OPE | I16: OPERATION | J16: P002 | K16: EOR | L16: 73 | M16: EOR STAFF | N16: EOR | O16: EOR | P16: POSTGRADUATE | Q16: POSTGRADUATE | R16: 01/09/2025 | S16: 1000000 | T16: 1000000 | AA16: 98300 | AB16: 10000 | AC16: 8921.16 | AE16: 268300 | AF16: 10000 | AG16: 1000000 | AH16: 117221.16 | AI16: 278300 | AJ16: 882778.84 | AK16: CRC | AM16: =SUM(T16:Z16)*3.89% -> 38900 | AN16: =+SUM(T16:Z16)/12 -> 83333.333
